localstripe/__init__.py
localstripe/__main__.py
localstripe/errors.py
localstripe/localstripe-v3.js
localstripe/resources.py
localstripe/server.py
localstripe/webhooks.py
localstripe-1.15.4.dist-info/LICENSE
localstripe-1.15.4.dist-info/METADATA
localstripe-1.15.4.dist-info/WHEEL
localstripe-1.15.4.dist-info/entry_points.txt
localstripe-1.15.4.dist-info/top_level.txt
localstripe-1.15.4.dist-info/RECORD
