Metadata-Version: 2.1
Name: localstripe
Version: 1.15.4
Summary: A fake but stateful Stripe server that you can run locally, for testing purposes.
Author: Adrien Vergé
License: GPL-3.0-or-later
Project-URL: homepage, https://github.com/adrienverge/localstripe
Project-URL: repository, https://github.com/adrienverge/localstripe
Project-URL: documentation, https://github.com/adrienverge/localstripe
Classifier: Development Status :: 5 - Production/Stable
Classifier: Intended Audience :: Developers
Classifier: Topic :: Software Development
Classifier: Topic :: Software Development :: Quality Assurance
Classifier: Topic :: Software Development :: Testing
Requires-Python: >=3.8
License-File: LICENSE
Requires-Dist: aiohttp >=2.3.2
Requires-Dist: python-dateutil >=2.6.1
Provides-Extra: dev
Requires-Dist: doc8 ; extra == 'dev'
Requires-Dist: flake8 ; extra == 'dev'
Requires-Dist: flake8-import-order ; extra == 'dev'
